GeeksforgeeksComputerOrganizationAndArchitectureLectureNotes/README.md
GeeksforgeeksComputerOrganizationAndArchitectureLectureNotes/__init__.py
GeeksforgeeksComputerOrganizationAndArchitectureLectureNotes/__main__.py
GeeksforgeeksComputerOrganizationAndArchitectureLectureNotes/file.epub
GeeksforgeeksComputerOrganizationAndArchitectureLectureNotes/index.html
GeeksforgeeksComputerOrganizationAndArchitectureLectureNotes/css/__init__.py
GeeksforgeeksComputerOrganizationAndArchitectureLectureNotes/css/annotations.css
GeeksforgeeksComputerOrganizationAndArchitectureLectureNotes/css/main.css
GeeksforgeeksComputerOrganizationAndArchitectureLectureNotes/css/normalize.css
GeeksforgeeksComputerOrganizationAndArchitectureLectureNotes/css/popup.css
GeeksforgeeksComputerOrganizationAndArchitectureLectureNotes/font/__init__.py
GeeksforgeeksComputerOrganizationAndArchitectureLectureNotes/font/fontello.eot
GeeksforgeeksComputerOrganizationAndArchitectureLectureNotes/font/fontello.svg
GeeksforgeeksComputerOrganizationAndArchitectureLectureNotes/font/fontello.ttf
GeeksforgeeksComputerOrganizationAndArchitectureLectureNotes/font/fontello.woff
GeeksforgeeksComputerOrganizationAndArchitectureLectureNotes/img/__init__.py
GeeksforgeeksComputerOrganizationAndArchitectureLectureNotes/img/annotator-glyph-sprite.png
GeeksforgeeksComputerOrganizationAndArchitectureLectureNotes/img/annotator-icon-sprite.png
GeeksforgeeksComputerOrganizationAndArchitectureLectureNotes/img/apple-touch-icon.png
GeeksforgeeksComputerOrganizationAndArchitectureLectureNotes/img/cancelfullscreen.png
GeeksforgeeksComputerOrganizationAndArchitectureLectureNotes/img/close.png
GeeksforgeeksComputerOrganizationAndArchitectureLectureNotes/img/fullscreen.png
GeeksforgeeksComputerOrganizationAndArchitectureLectureNotes/img/loader.gif
GeeksforgeeksComputerOrganizationAndArchitectureLectureNotes/img/menu-icon.png
GeeksforgeeksComputerOrganizationAndArchitectureLectureNotes/img/save.png
geeksforgeeks_computer_organization_and_architecture_lecture_notes-2024.3.3.0.dist-info/METADATA
geeksforgeeks_computer_organization_and_architecture_lecture_notes-2024.3.3.0.dist-info/WHEEL
geeksforgeeks_computer_organization_and_architecture_lecture_notes-2024.3.3.0.dist-info/entry_points.txt
geeksforgeeks_computer_organization_and_architecture_lecture_notes-2024.3.3.0.dist-info/top_level.txt
geeksforgeeks_computer_organization_and_architecture_lecture_notes-2024.3.3.0.dist-info/RECORD
